dbt_accelerator/__init__.py
dbt_accelerator/schema_md_generator/__init__.py
dbt_accelerator/schema_md_generator/create.py
dbt_accelerator-0.0.1.dist-info/LICENSE
dbt_accelerator-0.0.1.dist-info/METADATA
dbt_accelerator-0.0.1.dist-info/WHEEL
dbt_accelerator-0.0.1.dist-info/top_level.txt
dbt_accelerator-0.0.1.dist-info/RECORD
