Metadata-Version: 2.1
Name: dbt-accelerator
Version: 0.0.1
Summary: Package which generates schema.yml and columns.md from Excel Sheet
Home-page: https://github.com/ramgopalan/dbt_accelerator
Author: Ramgopalan V
Author-email: ram.gopalan@live.com
License: UNKNOWN
Platform: UNKNOWN
Classifier: Programming Language :: Python :: 3
Classifier: License :: OSI Approved :: MIT License
Classifier: Operating System :: OS Independent
Requires-Python: >=3.6
Requires-Dist: pandas
Requires-Dist: xlrd
Requires-Dist: mdutils
